[
  {
    "id": "DHAvBGhpa4A",
    "title": "Property Tour",
    "location": "Old Rajinder Nagar",
    "views": "",
    "category": "Buy / Rent",
    "type": "living"
  },
  {
    "id": "DG0fTJDJagC",
    "title": "Property Tour",
    "location": "Old Rajinder Nagar",
    "views": "",
    "category": "PG / Hostel",
    "type": "girls"
  },
  {
    "id": "DGw2yeQprZJ",
    "title": "Property Tour",
    "location": "Karol Bagh",
    "views": "",
    "category": "Commercial",
    "type": "commercial"
  },
  {
    "id": "DGpE_UOzw-s",
    "title": "Property Tour",
    "location": "New Rajinder Nagar",
    "views": "",
    "category": "Buy / Rent",
    "type": "living"
  },
  {
    "id": "DGkwy39p0y9",
    "title": "Property Tour",
    "location": "Old Rajinder Nagar",
    "views": "",
    "category": "PG / Hostel",
    "type": "girls"
  },
  {
    "id": "DGf8hCnTAt8",
    "title": "Property Tour",
    "location": "Karol Bagh",
    "views": "",
    "category": "Commercial",
    "type": "office"
  }
]
